LICENSE
README.txt
setup.py
classifygpt/__init__.py
classifygpt/classify.py
classifygpt.egg-info/PKG-INFO
classifygpt.egg-info/SOURCES.txt
classifygpt.egg-info/dependency_links.txt
classifygpt.egg-info/requires.txt
classifygpt.egg-info/top_level.txt