Metadata-Version: 2.1
Name: classifygpt
Version: 0.1
Summary: Classifying sentences as AI agent written or not
Home-page: https://github.com/AashaiAvadhani1/classifygpt
Download-URL: https://github.com/user/reponame/archive/v_01.tar.gz
Author: Aashai Avadhani
Author-email: aashai123@gmail.com
License: MIT
Keywords: SOME,MEANINGFULL,KEYWORDS
Classifier: Programming Language :: Python :: 3
Classifier: License :: OSI Approved :: MIT License
Classifier: Operating System :: OS Independent
Requires-Python: >=3.6
License-File: LICENSE
